{
  "Parameters": {
    "DynamoDBModelTableReadIOPS": {
      "Type": "Number",
      "Default": 5,
      "Description": "The number of read IOPS the table should support."
    },
    "DynamoDBModelTableWriteIOPS": {
      "Type": "Number",
      "Default": 5,
      "Description": "The number of write IOPS the table should support."
    },
    "DynamoDBBillingMode": {
      "Type": "String",
      "Default": "PAY_PER_REQUEST",
      "AllowedValues": [
        "PAY_PER_REQUEST",
        "PROVISIONED"
      ],
      "Description": "Configure @model types to create DynamoDB tables with PAY_PER_REQUEST or PROVISIONED billing modes."
    },
    "DynamoDBEnablePointInTimeRecovery": {
      "Type": "String",
      "Default": "false",
      "AllowedValues": [
        "true",
        "false"
      ],
      "Description": "Whether to enable Point in Time Recovery on the table."
    },
    "DynamoDBEnableServerSideEncryption": {
      "Type": "String",
      "Default": "true",
      "AllowedValues": [
        "true",
        "false"
      ],
      "Description": "Enable server side encryption powered by KMS."
    },
    "referencetotransformerrootstackenv10C5A902Ref": {
      "Type": "String"
    },
    "referencetotransformerrootstackGraphQLAPI20497F53ApiId": {
      "Type": "String"
    },
    "referencetotransformerrootstackGraphQLAPINONEDS2BA9D1C8Name": {
      "Type": "String"
    },
    "referencetotransformerrootstackS3DeploymentBucket7592718ARef": {
      "Type": "String"
    },
    "referencetotransformerrootstackS3DeploymentRootKeyA71EA735Ref": {
      "Type": "String"
    },
    "referencetotransformerrootstackauthRoleNameFB872D50Ref": {
      "Type": "String"
    },
    "referencetotransformerrootstackunauthRoleName49F3C1FERef": {
      "Type": "String"
    }
  },
  "Conditions": {
    "HasEnvironmentParameter": {
      "Fn::Not": [
        {
          "Fn::Equals": [
            {
              "Ref": "referencetotransformerrootstackenv10C5A902Ref"
            },
            "NONE"
          ]
        }
      ]
    },
    "ShouldUseServerSideEncryption": {
      "Fn::Equals": [
        {
          "Ref": "DynamoDBEnableServerSideEncryption"
        },
        "true"
      ]
    },
    "ShouldUsePayPerRequestBilling": {
      "Fn::Equals": [
        {
          "Ref": "DynamoDBBillingMode"
        },
        "PAY_PER_REQUEST"
      ]
    },
    "ShouldUsePointInTimeRecovery": {
      "Fn::Equals": [
        {
          "Ref": "DynamoDBEnablePointInTimeRecovery"
        },
        "true"
      ]
    }
  },
  "Resources": {
    "AttendanceListTable": {
      "Type": "AWS::DynamoDB::Table",
      "Properties": {
        "KeySchema": [
          {
            "AttributeName": "id",
            "KeyType": "HASH"
          }
        ],
        "AttributeDefinitions": [
          {
            "AttributeName": "id",
            "AttributeType": "S"
          }
        ],
        "BillingMode": {
          "Fn::If": [
            "ShouldUsePayPerRequestBilling",
            "PAY_PER_REQUEST",
            {
              "Ref": "AWS::NoValue"
            }
          ]
        },
        "PointInTimeRecoverySpecification": {
          "Fn::If": [
            "ShouldUsePointInTimeRecovery",
            {
              "PointInTimeRecoveryEnabled": true
            },
            {
              "Ref": "AWS::NoValue"
            }
          ]
        },
        "ProvisionedThroughput": {
          "Fn::If": [
            "ShouldUsePayPerRequestBilling",
            {
              "Ref": "AWS::NoValue"
            },
            {
              "ReadCapacityUnits": {
                "Ref": "DynamoDBModelTableReadIOPS"
              },
              "WriteCapacityUnits": {
                "Ref": "DynamoDBModelTableWriteIOPS"
              }
            }
          ]
        },
        "SSESpecification": {
          "SSEEnabled": {
            "Fn::If": [
              "ShouldUseServerSideEncryption",
              true,
              false
            ]
          }
        },
        "StreamSpecification": {
          "StreamViewType": "NEW_AND_OLD_IMAGES"
        },
        "TableName": {
          "Fn::Join": [
            "",
            [
              "AttendanceList-",
              {
                "Ref": "referencetotransformerrootstackGraphQLAPI20497F53ApiId"
              },
              "-",
              {
                "Ref": "referencetotransformerrootstackenv10C5A902Ref"
              }
            ]
          ]
        },
        "TimeToLiveSpecification": {
          "AttributeName": "_ttl",
          "Enabled": true
        }
      },
      "UpdateReplacePolicy": "Delete",
      "DeletionPolicy": "Delete"
    },
    "AttendanceListIAMRoleA8A87427": {
      "Type": "AWS::IAM::Role",
      "Properties": {
        "AssumeRolePolicyDocument": {
          "Statement": [
            {
              "Action": "sts:AssumeRole",
              "Effect": "Allow",
              "Principal": {
                "Service": "appsync.amazonaws.com"
              }
            }
          ],
          "Version": "2012-10-17"
        },
        "RoleName": {
          "Fn::Join": [
            "",
            [
              "AttendanceListIAMRolb3f253-",
              {
                "Ref": "referencetotransformerrootstackGraphQLAPI20497F53ApiId"
              },
              "-",
              {
                "Ref": "referencetotransformerrootstackenv10C5A902Ref"
              }
            ]
          ]
        }
      }
    },
    "AttendanceListIAMRoleDefaultPolicyDAAB52A1": {
      "Type": "AWS::IAM::Policy",
      "Properties": {
        "PolicyDocument": {
          "Statement": [
            {
              "Action": [
                "dynamodb:BatchGetItem",
                "dynamodb:GetRecords",
                "dynamodb:GetShardIterator",
                "dynamodb:Query",
                "dynamodb:GetItem",
                "dynamodb:Scan",
                "dynamodb:ConditionCheckItem",
                "dynamodb:BatchWriteItem",
                "dynamodb:PutItem",
                "dynamodb:UpdateItem",
                "dynamodb:DeleteItem"
              ],
              "Effect": "Allow",
              "Resource": [
                {
                  "Fn::GetAtt": [
                    "AttendanceListTable",
                    "Arn"
                  ]
                },
                {
                  "Ref": "AWS::NoValue"
                }
              ]
            }
          ],
          "Version": "2012-10-17"
        },
        "PolicyName": "AttendanceListIAMRoleDefaultPolicyDAAB52A1",
        "Roles": [
          {
            "Ref": "AttendanceListIAMRoleA8A87427"
          }
        ]
      }
    },
    "DynamoDBAccess71ABE5AE": {
      "Type": "AWS::IAM::Policy",
      "Properties": {
        "PolicyDocument": {
          "Statement": [
            {
              "Action": [
                "dynamodb:BatchGetItem",
                "dynamodb:BatchWriteItem",
                "dynamodb:PutItem",
                "dynamodb:DeleteItem",
                "dynamodb:GetItem",
                "dynamodb:Scan",
                "dynamodb:Query",
                "dynamodb:UpdateItem"
              ],
              "Effect": "Allow",
              "Resource": [
                {
                  "Fn::Sub": [
                    "arn:aws:dynamodb:${AWS::Region}:${AWS::AccountId}:table/${tablename}",
                    {
                      "tablename": {
                        "Fn::Join": [
                          "",
                          [
                            "AttendanceList-",
                            {
                              "Ref": "referencetotransformerrootstackGraphQLAPI20497F53ApiId"
                            },
                            "-",
                            {
                              "Ref": "referencetotransformerrootstackenv10C5A902Ref"
                            }
                          ]
                        ]
                      }
                    }
                  ]
                },
                {
                  "Fn::Sub": [
                    "arn:aws:dynamodb:${AWS::Region}:${AWS::AccountId}:table/${tablename}/*",
                    {
                      "tablename": {
                        "Fn::Join": [
                          "",
                          [
                            "AttendanceList-",
                            {
                              "Ref": "referencetotransformerrootstackGraphQLAPI20497F53ApiId"
                            },
                            "-",
                            {
                              "Ref": "referencetotransformerrootstackenv10C5A902Ref"
                            }
                          ]
                        ]
                      }
                    }
                  ]
                },
                {
                  "Fn::Sub": [
                    "arn:aws:dynamodb:${AWS::Region}:${AWS::AccountId}:table/${tablename}",
                    {
                      "tablename": {
                        "Fn::Join": [
                          "",
                          [
                            "AmplifyDataStore-",
                            {
                              "Ref": "referencetotransformerrootstackGraphQLAPI20497F53ApiId"
                            },
                            "-",
                            {
                              "Ref": "referencetotransformerrootstackenv10C5A902Ref"
                            }
                          ]
                        ]
                      }
                    }
                  ]
                },
                {
                  "Fn::Sub": [
                    "arn:aws:dynamodb:${AWS::Region}:${AWS::AccountId}:table/${tablename}/*",
                    {
                      "tablename": {
                        "Fn::Join": [
                          "",
                          [
                            "AmplifyDataStore-",
                            {
                              "Ref": "referencetotransformerrootstackGraphQLAPI20497F53ApiId"
                            },
                            "-",
                            {
                              "Ref": "referencetotransformerrootstackenv10C5A902Ref"
                            }
                          ]
                        ]
                      }
                    }
                  ]
                }
              ]
            }
          ],
          "Version": "2012-10-17"
        },
        "PolicyName": "DynamoDBAccess71ABE5AE",
        "Roles": [
          {
            "Ref": "AttendanceListIAMRoleA8A87427"
          }
        ]
      }
    },
    "AttendanceListDataSource": {
      "Type": "AWS::AppSync::DataSource",
      "Properties": {
        "ApiId": {
          "Ref": "referencetotransformerrootstackGraphQLAPI20497F53ApiId"
        },
        "Name": "AttendanceListTable",
        "Type": "AMAZON_DYNAMODB",
        "DynamoDBConfig": {
          "AwsRegion": {
            "Ref": "AWS::Region"
          },
          "DeltaSyncConfig": {
            "BaseTableTTL": "43200",
            "DeltaSyncTableName": {
              "Fn::Join": [
                "",
                [
                  "AmplifyDataStore-",
                  {
                    "Ref": "referencetotransformerrootstackGraphQLAPI20497F53ApiId"
                  },
                  "-",
                  {
                    "Ref": "referencetotransformerrootstackenv10C5A902Ref"
                  }
                ]
              ]
            },
            "DeltaSyncTableTTL": "30"
          },
          "TableName": {
            "Ref": "AttendanceListTable"
          },
          "Versioned": true
        },
        "ServiceRoleArn": {
          "Fn::GetAtt": [
            "AttendanceListIAMRoleA8A87427",
            "Arn"
          ]
        }
      },
      "DependsOn": [
        "AttendanceListIAMRoleA8A87427"
      ]
    },
    "QuerygetAttendanceListauth0FunctionQuerygetAttendanceListauth0FunctionAppSyncFunction623C48BD": {
      "Type": "AWS::AppSync::FunctionConfiguration",
      "Properties": {
        "ApiId": {
          "Ref": "referencetotransformerrootstackGraphQLAPI20497F53ApiId"
        },
        "DataSourceName": {
          "Ref": "referencetotransformerrootstackGraphQLAPINONEDS2BA9D1C8Name"
        },
        "FunctionVersion": "2018-05-29",
        "Name": "QuerygetAttendanceListauth0Function",
        "RequestMappingTemplateS3Location": {
          "Fn::Join": [
            "",
            [
              "s3://",
              {
                "Ref": "referencetotransformerrootstackS3DeploymentBucket7592718ARef"
              },
              "/",
              {
                "Ref": "referencetotransformerrootstackS3DeploymentRootKeyA71EA735Ref"
              },
              "/resolvers/Query.getAttendanceList.auth.1.req.vtl"
            ]
          ]
        },
        "ResponseMappingTemplate": "$util.toJson({})"
      }
    },
    "QuerygetAttendanceListpostAuth0FunctionQuerygetAttendanceListpostAuth0FunctionAppSyncFunction4D8D9E20": {
      "Type": "AWS::AppSync::FunctionConfiguration",
      "Properties": {
        "ApiId": {
          "Ref": "referencetotransformerrootstackGraphQLAPI20497F53ApiId"
        },
        "DataSourceName": {
          "Ref": "referencetotransformerrootstackGraphQLAPINONEDS2BA9D1C8Name"
        },
        "FunctionVersion": "2018-05-29",
        "Name": "QuerygetAttendanceListpostAuth0Function",
        "RequestMappingTemplateS3Location": {
          "Fn::Join": [
            "",
            [
              "s3://",
              {
                "Ref": "referencetotransformerrootstackS3DeploymentBucket7592718ARef"
              },
              "/",
              {
                "Ref": "referencetotransformerrootstackS3DeploymentRootKeyA71EA735Ref"
              },
              "/resolvers/Query.getAttendanceList.postAuth.1.req.vtl"
            ]
          ]
        },
        "ResponseMappingTemplate": "$util.toJson({})"
      }
    },
    "QueryGetAttendanceListDataResolverFnQueryGetAttendanceListDataResolverFnAppSyncFunction62B42F2B": {
      "Type": "AWS::AppSync::FunctionConfiguration",
      "Properties": {
        "ApiId": {
          "Ref": "referencetotransformerrootstackGraphQLAPI20497F53ApiId"
        },
        "DataSourceName": {
          "Fn::GetAtt": [
            "AttendanceListDataSource",
            "Name"
          ]
        },
        "FunctionVersion": "2018-05-29",
        "Name": "QueryGetAttendanceListDataResolverFn",
        "RequestMappingTemplateS3Location": {
          "Fn::Join": [
            "",
            [
              "s3://",
              {
                "Ref": "referencetotransformerrootstackS3DeploymentBucket7592718ARef"
              },
              "/",
              {
                "Ref": "referencetotransformerrootstackS3DeploymentRootKeyA71EA735Ref"
              },
              "/resolvers/Query.getAttendanceList.req.vtl"
            ]
          ]
        },
        "ResponseMappingTemplateS3Location": {
          "Fn::Join": [
            "",
            [
              "s3://",
              {
                "Ref": "referencetotransformerrootstackS3DeploymentBucket7592718ARef"
              },
              "/",
              {
                "Ref": "referencetotransformerrootstackS3DeploymentRootKeyA71EA735Ref"
              },
              "/resolvers/Query.getAttendanceList.res.vtl"
            ]
          ]
        },
        "SyncConfig": {
          "ConflictDetection": "VERSION",
          "ConflictHandler": "AUTOMERGE"
        }
      },
      "DependsOn": [
        "AttendanceListDataSource"
      ]
    },
    "GetAttendanceListResolver": {
      "Type": "AWS::AppSync::Resolver",
      "Properties": {
        "ApiId": {
          "Ref": "referencetotransformerrootstackGraphQLAPI20497F53ApiId"
        },
        "FieldName": "getAttendanceList",
        "TypeName": "Query",
        "Kind": "PIPELINE",
        "PipelineConfig": {
          "Functions": [
            {
              "Fn::GetAtt": [
                "QuerygetAttendanceListauth0FunctionQuerygetAttendanceListauth0FunctionAppSyncFunction623C48BD",
                "FunctionId"
              ]
            },
            {
              "Fn::GetAtt": [
                "QuerygetAttendanceListpostAuth0FunctionQuerygetAttendanceListpostAuth0FunctionAppSyncFunction4D8D9E20",
                "FunctionId"
              ]
            },
            {
              "Fn::GetAtt": [
                "QueryGetAttendanceListDataResolverFnQueryGetAttendanceListDataResolverFnAppSyncFunction62B42F2B",
                "FunctionId"
              ]
            }
          ]
        },
        "RequestMappingTemplate": {
          "Fn::Join": [
            "",
            [
              "$util.qr($ctx.stash.put(\"typeName\", \"Query\"))\n$util.qr($ctx.stash.put(\"fieldName\", \"getAttendanceList\"))\n$util.qr($ctx.stash.put(\"conditions\", []))\n$util.qr($ctx.stash.put(\"metadata\", {}))\n$util.qr($ctx.stash.metadata.put(\"dataSourceType\", \"AMAZON_DYNAMODB\"))\n$util.qr($ctx.stash.metadata.put(\"apiId\", \"",
              {
                "Ref": "referencetotransformerrootstackGraphQLAPI20497F53ApiId"
              },
              "\"))\n$util.qr($ctx.stash.put(\"tableName\", \"",
              {
                "Ref": "AttendanceListTable"
              },
              "\"))\n$util.qr($ctx.stash.put(\"authRole\", \"arn:aws:sts::",
              {
                "Ref": "AWS::AccountId"
              },
              ":assumed-role/",
              {
                "Ref": "referencetotransformerrootstackauthRoleNameFB872D50Ref"
              },
              "/CognitoIdentityCredentials\"))\n$util.qr($ctx.stash.put(\"unauthRole\", \"arn:aws:sts::",
              {
                "Ref": "AWS::AccountId"
              },
              ":assumed-role/",
              {
                "Ref": "referencetotransformerrootstackunauthRoleName49F3C1FERef"
              },
              "/CognitoIdentityCredentials\"))\n$util.toJson({})"
            ]
          ]
        },
        "ResponseMappingTemplate": "$util.toJson($ctx.prev.result)"
      }
    },
    "QueryListAttendanceListsDataResolverFnQueryListAttendanceListsDataResolverFnAppSyncFunction63585660": {
      "Type": "AWS::AppSync::FunctionConfiguration",
      "Properties": {
        "ApiId": {
          "Ref": "referencetotransformerrootstackGraphQLAPI20497F53ApiId"
        },
        "DataSourceName": {
          "Fn::GetAtt": [
            "AttendanceListDataSource",
            "Name"
          ]
        },
        "FunctionVersion": "2018-05-29",
        "Name": "QueryListAttendanceListsDataResolverFn",
        "RequestMappingTemplateS3Location": {
          "Fn::Join": [
            "",
            [
              "s3://",
              {
                "Ref": "referencetotransformerrootstackS3DeploymentBucket7592718ARef"
              },
              "/",
              {
                "Ref": "referencetotransformerrootstackS3DeploymentRootKeyA71EA735Ref"
              },
              "/resolvers/Query.listAttendanceLists.req.vtl"
            ]
          ]
        },
        "ResponseMappingTemplateS3Location": {
          "Fn::Join": [
            "",
            [
              "s3://",
              {
                "Ref": "referencetotransformerrootstackS3DeploymentBucket7592718ARef"
              },
              "/",
              {
                "Ref": "referencetotransformerrootstackS3DeploymentRootKeyA71EA735Ref"
              },
              "/resolvers/Query.listAttendanceLists.res.vtl"
            ]
          ]
        },
        "SyncConfig": {
          "ConflictDetection": "VERSION",
          "ConflictHandler": "AUTOMERGE"
        }
      },
      "DependsOn": [
        "AttendanceListDataSource"
      ]
    },
    "ListAttendanceListResolver": {
      "Type": "AWS::AppSync::Resolver",
      "Properties": {
        "ApiId": {
          "Ref": "referencetotransformerrootstackGraphQLAPI20497F53ApiId"
        },
        "FieldName": "listAttendanceLists",
        "TypeName": "Query",
        "Kind": "PIPELINE",
        "PipelineConfig": {
          "Functions": [
            {
              "Fn::GetAtt": [
                "QuerygetAttendanceListauth0FunctionQuerygetAttendanceListauth0FunctionAppSyncFunction623C48BD",
                "FunctionId"
              ]
            },
            {
              "Fn::GetAtt": [
                "QuerygetAttendanceListpostAuth0FunctionQuerygetAttendanceListpostAuth0FunctionAppSyncFunction4D8D9E20",
                "FunctionId"
              ]
            },
            {
              "Fn::GetAtt": [
                "QueryListAttendanceListsDataResolverFnQueryListAttendanceListsDataResolverFnAppSyncFunction63585660",
                "FunctionId"
              ]
            }
          ]
        },
        "RequestMappingTemplate": {
          "Fn::Join": [
            "",
            [
              "$util.qr($ctx.stash.put(\"typeName\", \"Query\"))\n$util.qr($ctx.stash.put(\"fieldName\", \"listAttendanceLists\"))\n$util.qr($ctx.stash.put(\"conditions\", []))\n$util.qr($ctx.stash.put(\"metadata\", {}))\n$util.qr($ctx.stash.metadata.put(\"dataSourceType\", \"AMAZON_DYNAMODB\"))\n$util.qr($ctx.stash.metadata.put(\"apiId\", \"",
              {
                "Ref": "referencetotransformerrootstackGraphQLAPI20497F53ApiId"
              },
              "\"))\n$util.qr($ctx.stash.put(\"tableName\", \"",
              {
                "Ref": "AttendanceListTable"
              },
              "\"))\n$util.qr($ctx.stash.put(\"authRole\", \"arn:aws:sts::",
              {
                "Ref": "AWS::AccountId"
              },
              ":assumed-role/",
              {
                "Ref": "referencetotransformerrootstackauthRoleNameFB872D50Ref"
              },
              "/CognitoIdentityCredentials\"))\n$util.qr($ctx.stash.put(\"unauthRole\", \"arn:aws:sts::",
              {
                "Ref": "AWS::AccountId"
              },
              ":assumed-role/",
              {
                "Ref": "referencetotransformerrootstackunauthRoleName49F3C1FERef"
              },
              "/CognitoIdentityCredentials\"))\n$util.toJson({})"
            ]
          ]
        },
        "ResponseMappingTemplate": "$util.toJson($ctx.prev.result)"
      }
    },
    "QuerySyncAttendanceListsDataResolverFnQuerySyncAttendanceListsDataResolverFnAppSyncFunction5FC3667E": {
      "Type": "AWS::AppSync::FunctionConfiguration",
      "Properties": {
        "ApiId": {
          "Ref": "referencetotransformerrootstackGraphQLAPI20497F53ApiId"
        },
        "DataSourceName": {
          "Fn::GetAtt": [
            "AttendanceListDataSource",
            "Name"
          ]
        },
        "FunctionVersion": "2018-05-29",
        "Name": "QuerySyncAttendanceListsDataResolverFn",
        "RequestMappingTemplateS3Location": {
          "Fn::Join": [
            "",
            [
              "s3://",
              {
                "Ref": "referencetotransformerrootstackS3DeploymentBucket7592718ARef"
              },
              "/",
              {
                "Ref": "referencetotransformerrootstackS3DeploymentRootKeyA71EA735Ref"
              },
              "/resolvers/Query.syncAttendanceLists.req.vtl"
            ]
          ]
        },
        "ResponseMappingTemplateS3Location": {
          "Fn::Join": [
            "",
            [
              "s3://",
              {
                "Ref": "referencetotransformerrootstackS3DeploymentBucket7592718ARef"
              },
              "/",
              {
                "Ref": "referencetotransformerrootstackS3DeploymentRootKeyA71EA735Ref"
              },
              "/resolvers/Query.syncAttendanceLists.res.vtl"
            ]
          ]
        },
        "SyncConfig": {
          "ConflictDetection": "VERSION",
          "ConflictHandler": "AUTOMERGE"
        }
      },
      "DependsOn": [
        "AttendanceListDataSource"
      ]
    },
    "SyncAttendanceListResolver": {
      "Type": "AWS::AppSync::Resolver",
      "Properties": {
        "ApiId": {
          "Ref": "referencetotransformerrootstackGraphQLAPI20497F53ApiId"
        },
        "FieldName": "syncAttendanceLists",
        "TypeName": "Query",
        "Kind": "PIPELINE",
        "PipelineConfig": {
          "Functions": [
            {
              "Fn::GetAtt": [
                "QuerygetAttendanceListauth0FunctionQuerygetAttendanceListauth0FunctionAppSyncFunction623C48BD",
                "FunctionId"
              ]
            },
            {
              "Fn::GetAtt": [
                "QuerygetAttendanceListpostAuth0FunctionQuerygetAttendanceListpostAuth0FunctionAppSyncFunction4D8D9E20",
                "FunctionId"
              ]
            },
            {
              "Fn::GetAtt": [
                "QuerySyncAttendanceListsDataResolverFnQuerySyncAttendanceListsDataResolverFnAppSyncFunction5FC3667E",
                "FunctionId"
              ]
            }
          ]
        },
        "RequestMappingTemplate": {
          "Fn::Join": [
            "",
            [
              "$util.qr($ctx.stash.put(\"typeName\", \"Query\"))\n$util.qr($ctx.stash.put(\"fieldName\", \"syncAttendanceLists\"))\n$util.qr($ctx.stash.put(\"conditions\", []))\n$util.qr($ctx.stash.put(\"metadata\", {}))\n$util.qr($ctx.stash.metadata.put(\"dataSourceType\", \"AMAZON_DYNAMODB\"))\n$util.qr($ctx.stash.metadata.put(\"apiId\", \"",
              {
                "Ref": "referencetotransformerrootstackGraphQLAPI20497F53ApiId"
              },
              "\"))\n$util.qr($ctx.stash.put(\"tableName\", \"",
              {
                "Ref": "AttendanceListTable"
              },
              "\"))\n$util.qr($ctx.stash.put(\"authRole\", \"arn:aws:sts::",
              {
                "Ref": "AWS::AccountId"
              },
              ":assumed-role/",
              {
                "Ref": "referencetotransformerrootstackauthRoleNameFB872D50Ref"
              },
              "/CognitoIdentityCredentials\"))\n$util.qr($ctx.stash.put(\"unauthRole\", \"arn:aws:sts::",
              {
                "Ref": "AWS::AccountId"
              },
              ":assumed-role/",
              {
                "Ref": "referencetotransformerrootstackunauthRoleName49F3C1FERef"
              },
              "/CognitoIdentityCredentials\"))\n$util.toJson({})"
            ]
          ]
        },
        "ResponseMappingTemplate": "$util.toJson($ctx.prev.result)"
      }
    },
    "MutationcreateAttendanceListinit0FunctionMutationcreateAttendanceListinit0FunctionAppSyncFunction47EF79EE": {
      "Type": "AWS::AppSync::FunctionConfiguration",
      "Properties": {
        "ApiId": {
          "Ref": "referencetotransformerrootstackGraphQLAPI20497F53ApiId"
        },
        "DataSourceName": {
          "Ref": "referencetotransformerrootstackGraphQLAPINONEDS2BA9D1C8Name"
        },
        "FunctionVersion": "2018-05-29",
        "Name": "MutationcreateAttendanceListinit0Function",
        "RequestMappingTemplateS3Location": {
          "Fn::Join": [
            "",
            [
              "s3://",
              {
                "Ref": "referencetotransformerrootstackS3DeploymentBucket7592718ARef"
              },
              "/",
              {
                "Ref": "referencetotransformerrootstackS3DeploymentRootKeyA71EA735Ref"
              },
              "/resolvers/Mutation.createAttendanceList.init.1.req.vtl"
            ]
          ]
        },
        "ResponseMappingTemplate": "$util.toJson({})"
      }
    },
    "MutationcreateAttendanceListauth0FunctionMutationcreateAttendanceListauth0FunctionAppSyncFunction942AA9F1": {
      "Type": "AWS::AppSync::FunctionConfiguration",
      "Properties": {
        "ApiId": {
          "Ref": "referencetotransformerrootstackGraphQLAPI20497F53ApiId"
        },
        "DataSourceName": {
          "Ref": "referencetotransformerrootstackGraphQLAPINONEDS2BA9D1C8Name"
        },
        "FunctionVersion": "2018-05-29",
        "Name": "MutationcreateAttendanceListauth0Function",
        "RequestMappingTemplateS3Location": {
          "Fn::Join": [
            "",
            [
              "s3://",
              {
                "Ref": "referencetotransformerrootstackS3DeploymentBucket7592718ARef"
              },
              "/",
              {
                "Ref": "referencetotransformerrootstackS3DeploymentRootKeyA71EA735Ref"
              },
              "/resolvers/Mutation.createAttendanceList.auth.1.req.vtl"
            ]
          ]
        },
        "ResponseMappingTemplate": "$util.toJson({})"
      }
    },
    "MutationCreateAttendanceListDataResolverFnMutationCreateAttendanceListDataResolverFnAppSyncFunctionA7C32B6A": {
      "Type": "AWS::AppSync::FunctionConfiguration",
      "Properties": {
        "ApiId": {
          "Ref": "referencetotransformerrootstackGraphQLAPI20497F53ApiId"
        },
        "DataSourceName": {
          "Fn::GetAtt": [
            "AttendanceListDataSource",
            "Name"
          ]
        },
        "FunctionVersion": "2018-05-29",
        "Name": "MutationCreateAttendanceListDataResolverFn",
        "RequestMappingTemplateS3Location": {
          "Fn::Join": [
            "",
            [
              "s3://",
              {
                "Ref": "referencetotransformerrootstackS3DeploymentBucket7592718ARef"
              },
              "/",
              {
                "Ref": "referencetotransformerrootstackS3DeploymentRootKeyA71EA735Ref"
              },
              "/resolvers/Mutation.createAttendanceList.req.vtl"
            ]
          ]
        },
        "ResponseMappingTemplateS3Location": {
          "Fn::Join": [
            "",
            [
              "s3://",
              {
                "Ref": "referencetotransformerrootstackS3DeploymentBucket7592718ARef"
              },
              "/",
              {
                "Ref": "referencetotransformerrootstackS3DeploymentRootKeyA71EA735Ref"
              },
              "/resolvers/Mutation.createAttendanceList.res.vtl"
            ]
          ]
        },
        "SyncConfig": {
          "ConflictDetection": "VERSION",
          "ConflictHandler": "AUTOMERGE"
        }
      },
      "DependsOn": [
        "AttendanceListDataSource"
      ]
    },
    "CreateAttendanceListResolver": {
      "Type": "AWS::AppSync::Resolver",
      "Properties": {
        "ApiId": {
          "Ref": "referencetotransformerrootstackGraphQLAPI20497F53ApiId"
        },
        "FieldName": "createAttendanceList",
        "TypeName": "Mutation",
        "Kind": "PIPELINE",
        "PipelineConfig": {
          "Functions": [
            {
              "Fn::GetAtt": [
                "MutationcreateAttendanceListinit0FunctionMutationcreateAttendanceListinit0FunctionAppSyncFunction47EF79EE",
                "FunctionId"
              ]
            },
            {
              "Fn::GetAtt": [
                "MutationcreateAttendanceListauth0FunctionMutationcreateAttendanceListauth0FunctionAppSyncFunction942AA9F1",
                "FunctionId"
              ]
            },
            {
              "Fn::GetAtt": [
                "QuerygetAttendanceListpostAuth0FunctionQuerygetAttendanceListpostAuth0FunctionAppSyncFunction4D8D9E20",
                "FunctionId"
              ]
            },
            {
              "Fn::GetAtt": [
                "MutationCreateAttendanceListDataResolverFnMutationCreateAttendanceListDataResolverFnAppSyncFunctionA7C32B6A",
                "FunctionId"
              ]
            }
          ]
        },
        "RequestMappingTemplate": {
          "Fn::Join": [
            "",
            [
              "$util.qr($ctx.stash.put(\"typeName\", \"Mutation\"))\n$util.qr($ctx.stash.put(\"fieldName\", \"createAttendanceList\"))\n$util.qr($ctx.stash.put(\"conditions\", []))\n$util.qr($ctx.stash.put(\"metadata\", {}))\n$util.qr($ctx.stash.metadata.put(\"dataSourceType\", \"AMAZON_DYNAMODB\"))\n$util.qr($ctx.stash.metadata.put(\"apiId\", \"",
              {
                "Ref": "referencetotransformerrootstackGraphQLAPI20497F53ApiId"
              },
              "\"))\n$util.qr($ctx.stash.put(\"tableName\", \"",
              {
                "Ref": "AttendanceListTable"
              },
              "\"))\n$util.qr($ctx.stash.put(\"authRole\", \"arn:aws:sts::",
              {
                "Ref": "AWS::AccountId"
              },
              ":assumed-role/",
              {
                "Ref": "referencetotransformerrootstackauthRoleNameFB872D50Ref"
              },
              "/CognitoIdentityCredentials\"))\n$util.qr($ctx.stash.put(\"unauthRole\", \"arn:aws:sts::",
              {
                "Ref": "AWS::AccountId"
              },
              ":assumed-role/",
              {
                "Ref": "referencetotransformerrootstackunauthRoleName49F3C1FERef"
              },
              "/CognitoIdentityCredentials\"))\n$util.toJson({})"
            ]
          ]
        },
        "ResponseMappingTemplate": "$util.toJson($ctx.prev.result)"
      }
    },
    "MutationupdateAttendanceListinit0FunctionMutationupdateAttendanceListinit0FunctionAppSyncFunctionE19E0E80": {
      "Type": "AWS::AppSync::FunctionConfiguration",
      "Properties": {
        "ApiId": {
          "Ref": "referencetotransformerrootstackGraphQLAPI20497F53ApiId"
        },
        "DataSourceName": {
          "Ref": "referencetotransformerrootstackGraphQLAPINONEDS2BA9D1C8Name"
        },
        "FunctionVersion": "2018-05-29",
        "Name": "MutationupdateAttendanceListinit0Function",
        "RequestMappingTemplateS3Location": {
          "Fn::Join": [
            "",
            [
              "s3://",
              {
                "Ref": "referencetotransformerrootstackS3DeploymentBucket7592718ARef"
              },
              "/",
              {
                "Ref": "referencetotransformerrootstackS3DeploymentRootKeyA71EA735Ref"
              },
              "/resolvers/Mutation.updateAttendanceList.init.1.req.vtl"
            ]
          ]
        },
        "ResponseMappingTemplate": "$util.toJson({})"
      }
    },
    "MutationupdateAttendanceListauth0FunctionMutationupdateAttendanceListauth0FunctionAppSyncFunction03A73CAB": {
      "Type": "AWS::AppSync::FunctionConfiguration",
      "Properties": {
        "ApiId": {
          "Ref": "referencetotransformerrootstackGraphQLAPI20497F53ApiId"
        },
        "DataSourceName": {
          "Fn::GetAtt": [
            "AttendanceListDataSource",
            "Name"
          ]
        },
        "FunctionVersion": "2018-05-29",
        "Name": "MutationupdateAttendanceListauth0Function",
        "RequestMappingTemplateS3Location": {
          "Fn::Join": [
            "",
            [
              "s3://",
              {
                "Ref": "referencetotransformerrootstackS3DeploymentBucket7592718ARef"
              },
              "/",
              {
                "Ref": "referencetotransformerrootstackS3DeploymentRootKeyA71EA735Ref"
              },
              "/resolvers/Mutation.updateAttendanceList.auth.1.req.vtl"
            ]
          ]
        },
        "ResponseMappingTemplateS3Location": {
          "Fn::Join": [
            "",
            [
              "s3://",
              {
                "Ref": "referencetotransformerrootstackS3DeploymentBucket7592718ARef"
              },
              "/",
              {
                "Ref": "referencetotransformerrootstackS3DeploymentRootKeyA71EA735Ref"
              },
              "/resolvers/Mutation.updateAttendanceList.auth.1.res.vtl"
            ]
          ]
        }
      },
      "DependsOn": [
        "AttendanceListDataSource"
      ]
    },
    "MutationUpdateAttendanceListDataResolverFnMutationUpdateAttendanceListDataResolverFnAppSyncFunction9DD3DA19": {
      "Type": "AWS::AppSync::FunctionConfiguration",
      "Properties": {
        "ApiId": {
          "Ref": "referencetotransformerrootstackGraphQLAPI20497F53ApiId"
        },
        "DataSourceName": {
          "Fn::GetAtt": [
            "AttendanceListDataSource",
            "Name"
          ]
        },
        "FunctionVersion": "2018-05-29",
        "Name": "MutationUpdateAttendanceListDataResolverFn",
        "RequestMappingTemplateS3Location": {
          "Fn::Join": [
            "",
            [
              "s3://",
              {
                "Ref": "referencetotransformerrootstackS3DeploymentBucket7592718ARef"
              },
              "/",
              {
                "Ref": "referencetotransformerrootstackS3DeploymentRootKeyA71EA735Ref"
              },
              "/resolvers/Mutation.updateAttendanceList.req.vtl"
            ]
          ]
        },
        "ResponseMappingTemplateS3Location": {
          "Fn::Join": [
            "",
            [
              "s3://",
              {
                "Ref": "referencetotransformerrootstackS3DeploymentBucket7592718ARef"
              },
              "/",
              {
                "Ref": "referencetotransformerrootstackS3DeploymentRootKeyA71EA735Ref"
              },
              "/resolvers/Mutation.updateAttendanceList.res.vtl"
            ]
          ]
        },
        "SyncConfig": {
          "ConflictDetection": "VERSION",
          "ConflictHandler": "AUTOMERGE"
        }
      },
      "DependsOn": [
        "AttendanceListDataSource"
      ]
    },
    "UpdateAttendanceListResolver": {
      "Type": "AWS::AppSync::Resolver",
      "Properties": {
        "ApiId": {
          "Ref": "referencetotransformerrootstackGraphQLAPI20497F53ApiId"
        },
        "FieldName": "updateAttendanceList",
        "TypeName": "Mutation",
        "Kind": "PIPELINE",
        "PipelineConfig": {
          "Functions": [
            {
              "Fn::GetAtt": [
                "MutationupdateAttendanceListinit0FunctionMutationupdateAttendanceListinit0FunctionAppSyncFunctionE19E0E80",
                "FunctionId"
              ]
            },
            {
              "Fn::GetAtt": [
                "MutationupdateAttendanceListauth0FunctionMutationupdateAttendanceListauth0FunctionAppSyncFunction03A73CAB",
                "FunctionId"
              ]
            },
            {
              "Fn::GetAtt": [
                "QuerygetAttendanceListpostAuth0FunctionQuerygetAttendanceListpostAuth0FunctionAppSyncFunction4D8D9E20",
                "FunctionId"
              ]
            },
            {
              "Fn::GetAtt": [
                "MutationUpdateAttendanceListDataResolverFnMutationUpdateAttendanceListDataResolverFnAppSyncFunction9DD3DA19",
                "FunctionId"
              ]
            }
          ]
        },
        "RequestMappingTemplate": {
          "Fn::Join": [
            "",
            [
              "$util.qr($ctx.stash.put(\"typeName\", \"Mutation\"))\n$util.qr($ctx.stash.put(\"fieldName\", \"updateAttendanceList\"))\n$util.qr($ctx.stash.put(\"conditions\", []))\n$util.qr($ctx.stash.put(\"metadata\", {}))\n$util.qr($ctx.stash.metadata.put(\"dataSourceType\", \"AMAZON_DYNAMODB\"))\n$util.qr($ctx.stash.metadata.put(\"apiId\", \"",
              {
                "Ref": "referencetotransformerrootstackGraphQLAPI20497F53ApiId"
              },
              "\"))\n$util.qr($ctx.stash.put(\"tableName\", \"",
              {
                "Ref": "AttendanceListTable"
              },
              "\"))\n$util.qr($ctx.stash.put(\"authRole\", \"arn:aws:sts::",
              {
                "Ref": "AWS::AccountId"
              },
              ":assumed-role/",
              {
                "Ref": "referencetotransformerrootstackauthRoleNameFB872D50Ref"
              },
              "/CognitoIdentityCredentials\"))\n$util.qr($ctx.stash.put(\"unauthRole\", \"arn:aws:sts::",
              {
                "Ref": "AWS::AccountId"
              },
              ":assumed-role/",
              {
                "Ref": "referencetotransformerrootstackunauthRoleName49F3C1FERef"
              },
              "/CognitoIdentityCredentials\"))\n$util.toJson({})"
            ]
          ]
        },
        "ResponseMappingTemplate": "$util.toJson($ctx.prev.result)"
      }
    },
    "MutationdeleteAttendanceListauth0FunctionMutationdeleteAttendanceListauth0FunctionAppSyncFunction5CA0EEDD": {
      "Type": "AWS::AppSync::FunctionConfiguration",
      "Properties": {
        "ApiId": {
          "Ref": "referencetotransformerrootstackGraphQLAPI20497F53ApiId"
        },
        "DataSourceName": {
          "Fn::GetAtt": [
            "AttendanceListDataSource",
            "Name"
          ]
        },
        "FunctionVersion": "2018-05-29",
        "Name": "MutationdeleteAttendanceListauth0Function",
        "RequestMappingTemplateS3Location": {
          "Fn::Join": [
            "",
            [
              "s3://",
              {
                "Ref": "referencetotransformerrootstackS3DeploymentBucket7592718ARef"
              },
              "/",
              {
                "Ref": "referencetotransformerrootstackS3DeploymentRootKeyA71EA735Ref"
              },
              "/resolvers/Mutation.deleteAttendanceList.auth.1.req.vtl"
            ]
          ]
        },
        "ResponseMappingTemplateS3Location": {
          "Fn::Join": [
            "",
            [
              "s3://",
              {
                "Ref": "referencetotransformerrootstackS3DeploymentBucket7592718ARef"
              },
              "/",
              {
                "Ref": "referencetotransformerrootstackS3DeploymentRootKeyA71EA735Ref"
              },
              "/resolvers/Mutation.deleteAttendanceList.auth.1.res.vtl"
            ]
          ]
        }
      },
      "DependsOn": [
        "AttendanceListDataSource"
      ]
    },
    "MutationDeleteAttendanceListDataResolverFnMutationDeleteAttendanceListDataResolverFnAppSyncFunction74FFE6BA": {
      "Type": "AWS::AppSync::FunctionConfiguration",
      "Properties": {
        "ApiId": {
          "Ref": "referencetotransformerrootstackGraphQLAPI20497F53ApiId"
        },
        "DataSourceName": {
          "Fn::GetAtt": [
            "AttendanceListDataSource",
            "Name"
          ]
        },
        "FunctionVersion": "2018-05-29",
        "Name": "MutationDeleteAttendanceListDataResolverFn",
        "RequestMappingTemplateS3Location": {
          "Fn::Join": [
            "",
            [
              "s3://",
              {
                "Ref": "referencetotransformerrootstackS3DeploymentBucket7592718ARef"
              },
              "/",
              {
                "Ref": "referencetotransformerrootstackS3DeploymentRootKeyA71EA735Ref"
              },
              "/resolvers/Mutation.deleteAttendanceList.req.vtl"
            ]
          ]
        },
        "ResponseMappingTemplateS3Location": {
          "Fn::Join": [
            "",
            [
              "s3://",
              {
                "Ref": "referencetotransformerrootstackS3DeploymentBucket7592718ARef"
              },
              "/",
              {
                "Ref": "referencetotransformerrootstackS3DeploymentRootKeyA71EA735Ref"
              },
              "/resolvers/Mutation.deleteAttendanceList.res.vtl"
            ]
          ]
        },
        "SyncConfig": {
          "ConflictDetection": "VERSION",
          "ConflictHandler": "AUTOMERGE"
        }
      },
      "DependsOn": [
        "AttendanceListDataSource"
      ]
    },
    "DeleteAttendanceListResolver": {
      "Type": "AWS::AppSync::Resolver",
      "Properties": {
        "ApiId": {
          "Ref": "referencetotransformerrootstackGraphQLAPI20497F53ApiId"
        },
        "FieldName": "deleteAttendanceList",
        "TypeName": "Mutation",
        "Kind": "PIPELINE",
        "PipelineConfig": {
          "Functions": [
            {
              "Fn::GetAtt": [
                "MutationdeleteAttendanceListauth0FunctionMutationdeleteAttendanceListauth0FunctionAppSyncFunction5CA0EEDD",
                "FunctionId"
              ]
            },
            {
              "Fn::GetAtt": [
                "QuerygetAttendanceListpostAuth0FunctionQuerygetAttendanceListpostAuth0FunctionAppSyncFunction4D8D9E20",
                "FunctionId"
              ]
            },
            {
              "Fn::GetAtt": [
                "MutationDeleteAttendanceListDataResolverFnMutationDeleteAttendanceListDataResolverFnAppSyncFunction74FFE6BA",
                "FunctionId"
              ]
            }
          ]
        },
        "RequestMappingTemplate": {
          "Fn::Join": [
            "",
            [
              "$util.qr($ctx.stash.put(\"typeName\", \"Mutation\"))\n$util.qr($ctx.stash.put(\"fieldName\", \"deleteAttendanceList\"))\n$util.qr($ctx.stash.put(\"conditions\", []))\n$util.qr($ctx.stash.put(\"metadata\", {}))\n$util.qr($ctx.stash.metadata.put(\"dataSourceType\", \"AMAZON_DYNAMODB\"))\n$util.qr($ctx.stash.metadata.put(\"apiId\", \"",
              {
                "Ref": "referencetotransformerrootstackGraphQLAPI20497F53ApiId"
              },
              "\"))\n$util.qr($ctx.stash.put(\"tableName\", \"",
              {
                "Ref": "AttendanceListTable"
              },
              "\"))\n$util.qr($ctx.stash.put(\"authRole\", \"arn:aws:sts::",
              {
                "Ref": "AWS::AccountId"
              },
              ":assumed-role/",
              {
                "Ref": "referencetotransformerrootstackauthRoleNameFB872D50Ref"
              },
              "/CognitoIdentityCredentials\"))\n$util.qr($ctx.stash.put(\"unauthRole\", \"arn:aws:sts::",
              {
                "Ref": "AWS::AccountId"
              },
              ":assumed-role/",
              {
                "Ref": "referencetotransformerrootstackunauthRoleName49F3C1FERef"
              },
              "/CognitoIdentityCredentials\"))\n$util.toJson({})"
            ]
          ]
        },
        "ResponseMappingTemplate": "$util.toJson($ctx.prev.result)"
      }
    },
    "SubscriptiononCreateAttendanceListauth0FunctionSubscriptiononCreateAttendanceListauth0FunctionAppSyncFunction3BA29122": {
      "Type": "AWS::AppSync::FunctionConfiguration",
      "Properties": {
        "ApiId": {
          "Ref": "referencetotransformerrootstackGraphQLAPI20497F53ApiId"
        },
        "DataSourceName": {
          "Ref": "referencetotransformerrootstackGraphQLAPINONEDS2BA9D1C8Name"
        },
        "FunctionVersion": "2018-05-29",
        "Name": "SubscriptiononCreateAttendanceListauth0Function",
        "RequestMappingTemplateS3Location": {
          "Fn::Join": [
            "",
            [
              "s3://",
              {
                "Ref": "referencetotransformerrootstackS3DeploymentBucket7592718ARef"
              },
              "/",
              {
                "Ref": "referencetotransformerrootstackS3DeploymentRootKeyA71EA735Ref"
              },
              "/resolvers/Subscription.onCreateAttendanceList.auth.1.req.vtl"
            ]
          ]
        },
        "ResponseMappingTemplate": "$util.toJson({})"
      }
    },
    "SubscriptionOnCreateAttendanceListDataResolverFnSubscriptionOnCreateAttendanceListDataResolverFnAppSyncFunction95BB6ACD": {
      "Type": "AWS::AppSync::FunctionConfiguration",
      "Properties": {
        "ApiId": {
          "Ref": "referencetotransformerrootstackGraphQLAPI20497F53ApiId"
        },
        "DataSourceName": {
          "Ref": "referencetotransformerrootstackGraphQLAPINONEDS2BA9D1C8Name"
        },
        "FunctionVersion": "2018-05-29",
        "Name": "SubscriptionOnCreateAttendanceListDataResolverFn",
        "RequestMappingTemplateS3Location": {
          "Fn::Join": [
            "",
            [
              "s3://",
              {
                "Ref": "referencetotransformerrootstackS3DeploymentBucket7592718ARef"
              },
              "/",
              {
                "Ref": "referencetotransformerrootstackS3DeploymentRootKeyA71EA735Ref"
              },
              "/resolvers/Subscription.onCreateAttendanceList.req.vtl"
            ]
          ]
        },
        "ResponseMappingTemplateS3Location": {
          "Fn::Join": [
            "",
            [
              "s3://",
              {
                "Ref": "referencetotransformerrootstackS3DeploymentBucket7592718ARef"
              },
              "/",
              {
                "Ref": "referencetotransformerrootstackS3DeploymentRootKeyA71EA735Ref"
              },
              "/resolvers/Subscription.onCreateAttendanceList.res.vtl"
            ]
          ]
        }
      }
    },
    "SubscriptiononCreateAttendanceListResolver": {
      "Type": "AWS::AppSync::Resolver",
      "Properties": {
        "ApiId": {
          "Ref": "referencetotransformerrootstackGraphQLAPI20497F53ApiId"
        },
        "FieldName": "onCreateAttendanceList",
        "TypeName": "Subscription",
        "Kind": "PIPELINE",
        "PipelineConfig": {
          "Functions": [
            {
              "Fn::GetAtt": [
                "SubscriptiononCreateAttendanceListauth0FunctionSubscriptiononCreateAttendanceListauth0FunctionAppSyncFunction3BA29122",
                "FunctionId"
              ]
            },
            {
              "Fn::GetAtt": [
                "QuerygetAttendanceListpostAuth0FunctionQuerygetAttendanceListpostAuth0FunctionAppSyncFunction4D8D9E20",
                "FunctionId"
              ]
            },
            {
              "Fn::GetAtt": [
                "SubscriptionOnCreateAttendanceListDataResolverFnSubscriptionOnCreateAttendanceListDataResolverFnAppSyncFunction95BB6ACD",
                "FunctionId"
              ]
            }
          ]
        },
        "RequestMappingTemplate": {
          "Fn::Join": [
            "",
            [
              "$util.qr($ctx.stash.put(\"typeName\", \"Subscription\"))\n$util.qr($ctx.stash.put(\"fieldName\", \"onCreateAttendanceList\"))\n$util.qr($ctx.stash.put(\"conditions\", []))\n$util.qr($ctx.stash.put(\"metadata\", {}))\n$util.qr($ctx.stash.metadata.put(\"dataSourceType\", \"NONE\"))\n$util.qr($ctx.stash.metadata.put(\"apiId\", \"",
              {
                "Ref": "referencetotransformerrootstackGraphQLAPI20497F53ApiId"
              },
              "\"))\n\n$util.qr($ctx.stash.put(\"authRole\", \"arn:aws:sts::",
              {
                "Ref": "AWS::AccountId"
              },
              ":assumed-role/",
              {
                "Ref": "referencetotransformerrootstackauthRoleNameFB872D50Ref"
              },
              "/CognitoIdentityCredentials\"))\n$util.qr($ctx.stash.put(\"unauthRole\", \"arn:aws:sts::",
              {
                "Ref": "AWS::AccountId"
              },
              ":assumed-role/",
              {
                "Ref": "referencetotransformerrootstackunauthRoleName49F3C1FERef"
              },
              "/CognitoIdentityCredentials\"))\n$util.toJson({})"
            ]
          ]
        },
        "ResponseMappingTemplate": "$util.toJson($ctx.prev.result)"
      }
    },
    "SubscriptiononUpdateAttendanceListResolver": {
      "Type": "AWS::AppSync::Resolver",
      "Properties": {
        "ApiId": {
          "Ref": "referencetotransformerrootstackGraphQLAPI20497F53ApiId"
        },
        "FieldName": "onUpdateAttendanceList",
        "TypeName": "Subscription",
        "Kind": "PIPELINE",
        "PipelineConfig": {
          "Functions": [
            {
              "Fn::GetAtt": [
                "SubscriptiononCreateAttendanceListauth0FunctionSubscriptiononCreateAttendanceListauth0FunctionAppSyncFunction3BA29122",
                "FunctionId"
              ]
            },
            {
              "Fn::GetAtt": [
                "QuerygetAttendanceListpostAuth0FunctionQuerygetAttendanceListpostAuth0FunctionAppSyncFunction4D8D9E20",
                "FunctionId"
              ]
            },
            {
              "Fn::GetAtt": [
                "SubscriptionOnCreateAttendanceListDataResolverFnSubscriptionOnCreateAttendanceListDataResolverFnAppSyncFunction95BB6ACD",
                "FunctionId"
              ]
            }
          ]
        },
        "RequestMappingTemplate": {
          "Fn::Join": [
            "",
            [
              "$util.qr($ctx.stash.put(\"typeName\", \"Subscription\"))\n$util.qr($ctx.stash.put(\"fieldName\", \"onUpdateAttendanceList\"))\n$util.qr($ctx.stash.put(\"conditions\", []))\n$util.qr($ctx.stash.put(\"metadata\", {}))\n$util.qr($ctx.stash.metadata.put(\"dataSourceType\", \"NONE\"))\n$util.qr($ctx.stash.metadata.put(\"apiId\", \"",
              {
                "Ref": "referencetotransformerrootstackGraphQLAPI20497F53ApiId"
              },
              "\"))\n\n$util.qr($ctx.stash.put(\"authRole\", \"arn:aws:sts::",
              {
                "Ref": "AWS::AccountId"
              },
              ":assumed-role/",
              {
                "Ref": "referencetotransformerrootstackauthRoleNameFB872D50Ref"
              },
              "/CognitoIdentityCredentials\"))\n$util.qr($ctx.stash.put(\"unauthRole\", \"arn:aws:sts::",
              {
                "Ref": "AWS::AccountId"
              },
              ":assumed-role/",
              {
                "Ref": "referencetotransformerrootstackunauthRoleName49F3C1FERef"
              },
              "/CognitoIdentityCredentials\"))\n$util.toJson({})"
            ]
          ]
        },
        "ResponseMappingTemplate": "$util.toJson($ctx.prev.result)"
      }
    },
    "SubscriptiononDeleteAttendanceListResolver": {
      "Type": "AWS::AppSync::Resolver",
      "Properties": {
        "ApiId": {
          "Ref": "referencetotransformerrootstackGraphQLAPI20497F53ApiId"
        },
        "FieldName": "onDeleteAttendanceList",
        "TypeName": "Subscription",
        "Kind": "PIPELINE",
        "PipelineConfig": {
          "Functions": [
            {
              "Fn::GetAtt": [
                "SubscriptiononCreateAttendanceListauth0FunctionSubscriptiononCreateAttendanceListauth0FunctionAppSyncFunction3BA29122",
                "FunctionId"
              ]
            },
            {
              "Fn::GetAtt": [
                "QuerygetAttendanceListpostAuth0FunctionQuerygetAttendanceListpostAuth0FunctionAppSyncFunction4D8D9E20",
                "FunctionId"
              ]
            },
            {
              "Fn::GetAtt": [
                "SubscriptionOnCreateAttendanceListDataResolverFnSubscriptionOnCreateAttendanceListDataResolverFnAppSyncFunction95BB6ACD",
                "FunctionId"
              ]
            }
          ]
        },
        "RequestMappingTemplate": {
          "Fn::Join": [
            "",
            [
              "$util.qr($ctx.stash.put(\"typeName\", \"Subscription\"))\n$util.qr($ctx.stash.put(\"fieldName\", \"onDeleteAttendanceList\"))\n$util.qr($ctx.stash.put(\"conditions\", []))\n$util.qr($ctx.stash.put(\"metadata\", {}))\n$util.qr($ctx.stash.metadata.put(\"dataSourceType\", \"NONE\"))\n$util.qr($ctx.stash.metadata.put(\"apiId\", \"",
              {
                "Ref": "referencetotransformerrootstackGraphQLAPI20497F53ApiId"
              },
              "\"))\n\n$util.qr($ctx.stash.put(\"authRole\", \"arn:aws:sts::",
              {
                "Ref": "AWS::AccountId"
              },
              ":assumed-role/",
              {
                "Ref": "referencetotransformerrootstackauthRoleNameFB872D50Ref"
              },
              "/CognitoIdentityCredentials\"))\n$util.qr($ctx.stash.put(\"unauthRole\", \"arn:aws:sts::",
              {
                "Ref": "AWS::AccountId"
              },
              ":assumed-role/",
              {
                "Ref": "referencetotransformerrootstackunauthRoleName49F3C1FERef"
              },
              "/CognitoIdentityCredentials\"))\n$util.toJson({})"
            ]
          ]
        },
        "ResponseMappingTemplate": "$util.toJson($ctx.prev.result)"
      }
    }
  },
  "Outputs": {
    "GetAttAttendanceListTableStreamArn": {
      "Description": "Your DynamoDB table StreamArn.",
      "Value": {
        "Fn::GetAtt": [
          "AttendanceListTable",
          "StreamArn"
        ]
      },
      "Export": {
        "Name": {
          "Fn::Join": [
            ":",
            [
              {
                "Ref": "referencetotransformerrootstackGraphQLAPI20497F53ApiId"
              },
              "GetAtt:AttendanceListTable:StreamArn"
            ]
          ]
        }
      }
    },
    "GetAttAttendanceListTableName": {
      "Description": "Your DynamoDB table name.",
      "Value": {
        "Ref": "AttendanceListTable"
      },
      "Export": {
        "Name": {
          "Fn::Join": [
            ":",
            [
              {
                "Ref": "referencetotransformerrootstackGraphQLAPI20497F53ApiId"
              },
              "GetAtt:AttendanceListTable:Name"
            ]
          ]
        }
      }
    },
    "GetAttAttendanceListDataSourceName": {
      "Description": "Your model DataSource name.",
      "Value": {
        "Fn::GetAtt": [
          "AttendanceListDataSource",
          "Name"
        ]
      },
      "Export": {
        "Name": {
          "Fn::Join": [
            ":",
            [
              {
                "Ref": "referencetotransformerrootstackGraphQLAPI20497F53ApiId"
              },
              "GetAtt:AttendanceListDataSource:Name"
            ]
          ]
        }
      }
    },
    "transformerrootstackAttendanceListQuerygetAttendanceListauth0FunctionQuerygetAttendanceListauth0FunctionAppSyncFunction1AC79632FunctionId": {
      "Value": {
        "Fn::GetAtt": [
          "QuerygetAttendanceListauth0FunctionQuerygetAttendanceListauth0FunctionAppSyncFunction623C48BD",
          "FunctionId"
        ]
      }
    },
    "transformerrootstackAttendanceListQuerygetAttendanceListpostAuth0FunctionQuerygetAttendanceListpostAuth0FunctionAppSyncFunction3841695BFunctionId": {
      "Value": {
        "Fn::GetAtt": [
          "QuerygetAttendanceListpostAuth0FunctionQuerygetAttendanceListpostAuth0FunctionAppSyncFunction4D8D9E20",
          "FunctionId"
        ]
      }
    },
    "transformerrootstackAttendanceListMutationcreateAttendanceListinit0FunctionMutationcreateAttendanceListinit0FunctionAppSyncFunction19477588FunctionId": {
      "Value": {
        "Fn::GetAtt": [
          "MutationcreateAttendanceListinit0FunctionMutationcreateAttendanceListinit0FunctionAppSyncFunction47EF79EE",
          "FunctionId"
        ]
      }
    },
    "transformerrootstackAttendanceListMutationcreateAttendanceListauth0FunctionMutationcreateAttendanceListauth0FunctionAppSyncFunctionFC092E9AFunctionId": {
      "Value": {
        "Fn::GetAtt": [
          "MutationcreateAttendanceListauth0FunctionMutationcreateAttendanceListauth0FunctionAppSyncFunction942AA9F1",
          "FunctionId"
        ]
      }
    },
    "transformerrootstackAttendanceListMutationupdateAttendanceListinit0FunctionMutationupdateAttendanceListinit0FunctionAppSyncFunctionD56AA3B1FunctionId": {
      "Value": {
        "Fn::GetAtt": [
          "MutationupdateAttendanceListinit0FunctionMutationupdateAttendanceListinit0FunctionAppSyncFunctionE19E0E80",
          "FunctionId"
        ]
      }
    },
    "transformerrootstackAttendanceListSubscriptiononCreateAttendanceListauth0FunctionSubscriptiononCreateAttendanceListauth0FunctionAppSyncFunction5AC49EF6FunctionId": {
      "Value": {
        "Fn::GetAtt": [
          "SubscriptiononCreateAttendanceListauth0FunctionSubscriptiononCreateAttendanceListauth0FunctionAppSyncFunction3BA29122",
          "FunctionId"
        ]
      }
    },
    "transformerrootstackAttendanceListSubscriptionOnCreateAttendanceListDataResolverFnSubscriptionOnCreateAttendanceListDataResolverFnAppSyncFunction821E7374FunctionId": {
      "Value": {
        "Fn::GetAtt": [
          "SubscriptionOnCreateAttendanceListDataResolverFnSubscriptionOnCreateAttendanceListDataResolverFnAppSyncFunction95BB6ACD",
          "FunctionId"
        ]
      }
    }
  }
}